<?xml version="1.0" encoding="UTF-8"?>

<?--
<Global>
    <debug_log_path>/var/log/api/fly_debug.log</debug_log_path>
    <info_log_path>/var/log/api/fly_info.log</info_log_path>
    <error_log_path>/var/log/api/fly_error.log</error_log_path>
    <poll_size>1024</poll_size>
</Global>

<fy_http_lomark_module>
    <http_conn_pool_size>32</http_conn_pool_size>
    <http_conn_addr>api.lomark.cn</http_conn_addr>
    <http_conn_location>/v2/get</http_conn_location>
    <http_conn_port>80</http_conn_port>
    <lomark_key>06ED59022B5245F58179F9BBAB1F2A23</lomark_key>
    <lomark_secret_key>17C942F6766A4BA089C8332A1906CBD3</lomark_secret_key>
</fy_http_lomark_module>
--?>

<Global>
    <debug_log_path>/var/log/api/fly_debug.log</debug_log_path>
    <info_log_path>/var/log/api/fly_info.log</info_log_path>
    <error_log_path>/var/log/api/fly_error.log</error_log_path>
    <poll_size>4096</poll_size>
</Global>

<fy_graph_module>
    <duration>3</duration>
    <adid>0001</adid>
    <tracker>http://tracker.cn</tracker>
    <graph_addr>http://qingtingpic.qiniudn.com/14_12_3_4.jpg</graph_addr>
    <!-- <graph_addr></graph_addr> -->
</fy_graph_module>

<?--
<fy_http_lomark_module>
    <http_conn_pool_size>32</http_conn_pool_size>
    <http_conn_addr>api.lomark.cn</http_conn_addr>
    <http_conn_location>/v2/get</http_conn_location>
    <http_conn_port>80</http_conn_port>
    <lomark_key>06ED59022B5245F58179F9BBAB1F2A23</lomark_key>
    <lomark_secret_key>17C942F6766A4BA089C8332A1906CBD3</lomark_secret_key>
</fy_http_lomark_module>
--?>

